Metadata-Version: 2.4
Name: iflow-mcp_uniprot-mcp-server
Version: 0.1.0
Summary: MCP server for UniProt protein data access
Author: UniProt MCP Server Contributors
License-Expression: MIT
License-File: LICENSE
Requires-Python: >=3.10
Requires-Dist: httpx
Requires-Dist: mcp
Provides-Extra: dev
Requires-Dist: bandit; extra == 'dev'
Requires-Dist: black; extra == 'dev'
Requires-Dist: flake8; extra == 'dev'
Requires-Dist: isort; extra == 'dev'
Requires-Dist: mypy; extra == 'dev'
Requires-Dist: pytest-asyncio; extra == 'dev'
Requires-Dist: pytest>=7.0; extra == 'dev'
Requires-Dist: safety; extra == 'dev'
